{
  "parent": "minecraft:recipes/root",
  "rewards": {
    "recipes": [
      "minecraft:tin_knife_from_ingots_tin"
    ]
  },
  "criteria": {
    "has_ingots_tin": {
      "trigger": "minecraft:inventory_changed",
      "conditions": {
        "items": [
          {
            "tag": "forge:ingots/tin"
          }
        ]
      }
    },
    "has_the_recipe": {
      "trigger": "minecraft:recipe_unlocked",
      "conditions": {
        "recipe": "minecraft:tin_knife_from_ingots_tin"
      }
    }
  },
  "requirements": [
    [
      "has_ingots_tin",
      "has_the_recipe"
    ]
  ]
}