{
  "parent": "minecraft:recipes/root",
  "rewards": {
    "recipes": [
      "mysticalworld:rose_cordial"
    ]
  },
  "criteria": {
    "has_first": {
      "trigger": "minecraft:inventory_changed",
      "conditions": {
        "items": [
          {
            "items": [
              "minecraft:rose_bush"
            ]
          }
        ]
      }
    },
    "has_sugar": {
      "trigger": "minecraft:inventory_changed",
      "conditions": {
        "items": [
          {
            "items": [
              "minecraft:sugar"
            ]
          }
        ]
      }
    },
    "has_the_recipe": {
      "trigger": "minecraft:recipe_unlocked",
      "conditions": {
        "recipe": "mysticalworld:rose_cordial"
      }
    }
  },
  "requirements": [
    [
      "has_first",
      "has_sugar",
      "has_the_recipe"
    ]
  ]
}