{
  "parent": "minecraft:recipes/root",
  "rewards": {
    "recipes": [
      "mysticalworld:storage_blocks_pearl_to_9_ingots"
    ]
  },
  "criteria": {
    "has_block_storage_blocks_pearl": {
      "trigger": "minecraft:inventory_changed",
      "conditions": {
        "items": [
          {
            "tag": "forge:storage_blocks/pearl"
          }
        ]
      }
    },
    "has_the_recipe": {
      "trigger": "minecraft:recipe_unlocked",
      "conditions": {
        "recipe": "mysticalworld:storage_blocks_pearl_to_9_ingots"
      }
    }
  },
  "requirements": [
    [
      "has_block_storage_blocks_pearl",
      "has_the_recipe"
    ]
  ]
}